README.rst
setup.py
ofpstr/__init__.py
ofpstr/cli.py
ofpstr/nx.py
ofpstr/ofp4.py
ofpstr/oxm.py
ofpstr/util.py
ofpstr.egg-info/PKG-INFO
ofpstr.egg-info/SOURCES.txt
ofpstr.egg-info/dependency_links.txt
ofpstr.egg-info/entry_points.txt
ofpstr.egg-info/top_level.txt
test/test_ofp4.py
test/test_ofp4_mp.py
test/test_oxm.py
test/test_util.py