Metadata-Version: 1.0
Name: ofpstr
Version: 0.2.0
Summary: Openflow stringer library
Home-page: https://github.com/hkwi/ofpstr/
Author: Hiroaki Kawai
Author-email: hiroaki.kawai@gmail.com
License: UNKNOWN
Platform: UNKNOWN
